<!--
     This is example metadata only. Do *NOT* supply it as is without review,
and do *NOT* provide it in real time to your partners.
 -->
<md:EntityDescriptor xmlns:md="urn:oasis:names:tc:SAML:2.0:metadata" ID="_657cf08a6730ac2e70ce094b8262cdf79ce25120" entityID="https://sp.example.org/shibboleth">

  <md:Extensions xmlns:alg="urn:oasis:names:tc:SAML:metadata:algsupport">
    <alg:DigestMethod Algorithm="http://www.w3.org/2001/04/xmlenc#sha512"/>
    <alg:DigestMethod Algorithm="http://www.w3.org/2001/04/xmldsig-more#sha384"/>
    <alg:DigestMethod Algorithm="http://www.w3.org/2001/04/xmlenc#sha256"/>
    <alg:DigestMethod Algorithm="http://www.w3.org/2001/04/xmldsig-more#sha224"/>
    <alg:DigestMethod Algorithm="http://www.w3.org/2000/09/xmldsig#sha1"/>
    <alg:SigningMethod Algorithm="http://www.w3.org/2001/04/xmldsig-more#ecdsa-sha512"/>
    <alg:SigningMethod Algorithm="http://www.w3.org/2001/04/xmldsig-more#ecdsa-sha384"/>
    <alg:SigningMethod Algorithm="http://www.w3.org/2001/04/xmldsig-more#ecdsa-sha256"/>
    <alg:SigningMethod Algorithm="http://www.w3.org/2001/04/xmldsig-more#ecdsa-sha224"/>
    <alg:SigningMethod Algorithm="http://www.w3.org/2001/04/xmldsig-more#rsa-sha512"/>
    <alg:SigningMethod Algorithm="http://www.w3.org/2001/04/xmldsig-more#rsa-sha384"/>
    <alg:SigningMethod Algorithm="http://www.w3.org/2001/04/xmldsig-more#rsa-sha256"/>
    <alg:SigningMethod Algorithm="http://www.w3.org/2009/xmldsig11#dsa-sha256"/>
    <alg:SigningMethod Algorithm="http://www.w3.org/2001/04/xmldsig-more#ecdsa-sha1"/>
    <alg:SigningMethod Algorithm="http://www.w3.org/2000/09/xmldsig#rsa-sha1"/>
    <alg:SigningMethod Algorithm="http://www.w3.org/2000/09/xmldsig#dsa-sha1"/>
  </md:Extensions>

  <md:SPSSODescriptor protocolSupportEnumeration="urn:oasis:names:tc:SAML:2.0:protocol urn:oasis:names:tc:SAML:1.1:protocol urn:oasis:names:tc:SAML:1.0:protocol">
    <md:Extensions>
      <init:RequestInitiator xmlns:init="urn:oasis:names:tc:SAML:profiles:SSO:request-init" Binding="urn:oasis:names:tc:SAML:profiles:SSO:request-init" Location="http://shibboleth/Shibboleth.sso/Login"/>
      <idpdisc:DiscoveryResponse xmlns:idpdisc="urn:oasis:names:tc:SAML:profiles:SSO:idp-discovery-protocol" Binding="urn:oasis:names:tc:SAML:profiles:SSO:idp-discovery-protocol" Location="http://shibboleth/Shibboleth.sso/Login" index="1"/>
    </md:Extensions>
    <md:KeyDescriptor>
      <ds:KeyInfo xmlns:ds="http://www.w3.org/2000/09/xmldsig#">
        <ds:KeyName>545cb0ebeb25</ds:KeyName>
        <ds:X509Data>
          <ds:X509SubjectName>CN=545cb0ebeb25</ds:X509SubjectName>
          <ds:X509Certificate>MIIC6zCCAdOgAwIBAgIJAIcottHTF/E4MA0GCSqGSIb3DQEBBQUAMBcxFTATBgNV
BAMTDDU0NWNiMGViZWIyNTAeFw0xNTA4MjAyMDI2MjhaFw0yNTA4MTcyMDI2Mjha
MBcxFTATBgNVBAMTDDU0NWNiMGViZWIyNTCCASIwDQYJKoZIhvcNAQEBBQADggEP
ADCCAQoCggEBALPjgsE4GKjfF479dEjALLMVf683HdQw+FcHpp9OEA15LmCCkvaO
Y6XqyLECdM0uuR0B8rSI0q9WQ8sIKulqAnADQI0QO096wM/fI3xL9RLFn6JMrN51
Wzj2JqkkadyyTzduEbOui1HncBiQ5enGgHcdzY7w86w7yJvzvMOURhYGAJKFoCD0
iN8daymDRvFpGNYTPJUA9LdBaGz9yD1S/uIvaAX+VaOzNpVDe2tM6vTeUU0FxRN2
CUxLZYJTEegVZG4VofMuHrd6TFYVRcjzDOib58M6VQIqEzEYqCocLIIJoWuVdJQi
9LXhw/pGpD072y2RNmCDitM55cVhxTadOBUCAwEAAaM6MDgwFwYDVR0RBBAwDoIM
NTQ1Y2IwZWJlYjI1MB0GA1UdDgQWBBQV2ZWi0O+DwwAWRZWHrCpA+ZMcJzANBgkq
hkiG9w0BAQUFAAOCAQEAjO7B7W4G0qEpH2vOPhm1R2hMfCxW+DUIQpmbL0WFojEs
zFSM/GEa+Mq/f8CiaqgBgOLIVjQclZnC27G7HDquBD0+2k8A64DMMYgDs9gdUaes
9B1F7iLa04ejrPLcfppRKE/ygcD4eCgFWFwdfPQqXVGkksUTX2xLXEdlqsLbFC/p
4IIqT6I5ACTNsZ7Bf6WE2q4agsYTM3qA76dEVXNi1nLCT231FVFfGGdG+AmqeNy1
6qYSnPum8/oEB3u83HdM4hUnotR4z+J97BAYBXmg20AttUp8W94CUgCxD1RMk5oQ
wcfhyqF7rzUv0Qp1mxpHqnxE7r6RpnDxVUhulEvLuQ==
</ds:X509Certificate>
        </ds:X509Data>
      </ds:KeyInfo>
      <md:EncryptionMethod Algorithm="http://www.w3.org/2009/xmlenc11#aes128-gcm"/>
      <md:EncryptionMethod Algorithm="http://www.w3.org/2009/xmlenc11#aes192-gcm"/>
      <md:EncryptionMethod Algorithm="http://www.w3.org/2009/xmlenc11#aes256-gcm"/>
      <md:EncryptionMethod Algorithm="http://www.w3.org/2001/04/xmlenc#aes128-cbc"/>
      <md:EncryptionMethod Algorithm="http://www.w3.org/2001/04/xmlenc#aes192-cbc"/>
      <md:EncryptionMethod Algorithm="http://www.w3.org/2001/04/xmlenc#aes256-cbc"/>
      <md:EncryptionMethod Algorithm="http://www.w3.org/2001/04/xmlenc#tripledes-cbc"/>
      <md:EncryptionMethod Algorithm="http://www.w3.org/2009/xmlenc11#rsa-oaep"/>
      <md:EncryptionMethod Algorithm="http://www.w3.org/2001/04/xmlenc#rsa-oaep-mgf1p"/>
    </md:KeyDescriptor>
    <md:ArtifactResolutionService Binding="urn:oasis:names:tc:SAML:2.0:bindings:SOAP" Location="http://shibboleth/Shibboleth.sso/Artifact/SOAP" index="1"/>
    <md:SingleLogoutService Binding="urn:oasis:names:tc:SAML:2.0:bindings:SOAP" Location="http://shibboleth/Shibboleth.sso/SLO/SOAP"/>
    <md:SingleLogoutService Binding="urn:oasis:names:tc:SAML:2.0:bindings:HTTP-Redirect" Location="http://shibboleth/Shibboleth.sso/SLO/Redirect"/>
    <md:SingleLogoutService Binding="urn:oasis:names:tc:SAML:2.0:bindings:HTTP-POST" Location="http://shibboleth/Shibboleth.sso/SLO/POST"/>
    <md:SingleLogoutService Binding="urn:oasis:names:tc:SAML:2.0:bindings:HTTP-Artifact" Location="http://shibboleth/Shibboleth.sso/SLO/Artifact"/>
    <md:AssertionConsumerService Binding="urn:oasis:names:tc:SAML:2.0:bindings:HTTP-POST" Location="http://shibboleth/Shibboleth.sso/SAML2/POST" index="1"/>
    <md:AssertionConsumerService Binding="urn:oasis:names:tc:SAML:2.0:bindings:HTTP-POST-SimpleSign" Location="http://shibboleth/Shibboleth.sso/SAML2/POST-SimpleSign" index="2"/>
    <md:AssertionConsumerService Binding="urn:oasis:names:tc:SAML:2.0:bindings:HTTP-Artifact" Location="http://shibboleth/Shibboleth.sso/SAML2/Artifact" index="3"/>
    <md:AssertionConsumerService Binding="urn:oasis:names:tc:SAML:2.0:bindings:PAOS" Location="http://shibboleth/Shibboleth.sso/SAML2/ECP" index="4"/>
    <md:AssertionConsumerService Binding="urn:oasis:names:tc:SAML:1.0:profiles:browser-post" Location="http://shibboleth/Shibboleth.sso/SAML/POST" index="5"/>
    <md:AssertionConsumerService Binding="urn:oasis:names:tc:SAML:1.0:profiles:artifact-01" Location="http://shibboleth/Shibboleth.sso/SAML/Artifact" index="6"/>
  </md:SPSSODescriptor>

</md:EntityDescriptor>
